README.md
cobhan/__init__.py
cobhan/cobhan.py
cobhan-0.4.3.dist-info/LICENSE
cobhan-0.4.3.dist-info/METADATA
cobhan-0.4.3.dist-info/WHEEL
cobhan-0.4.3.dist-info/RECORD
