Metadata-Version: 2.1
Name: cobhan
Version: 0.4.3
Summary: Cobhan FFI
Home-page: https://github.com/godaddy/cobhan-python/
License: MIT
Keywords: ffi
Author: Jeremiah Gowdy
Author-email: jeremiah@gowdy.me
Maintainer: GoDaddy
Maintainer-email: oss@godaddy.com
Requires-Python: >=3.7,<4.0
Classifier: License :: OSI Approved :: MIT License
Classifier: Programming Language :: Python :: 3
Classifier: Programming Language :: Python :: 3.7
Classifier: Programming Language :: Python :: 3.8
Classifier: Programming Language :: Python :: 3.9
Classifier: Programming Language :: Python :: 3.10
Classifier: Programming Language :: Python :: 3.11
Requires-Dist: cffi (>=1.15.0,<2.0.0)
Project-URL: Repository, https://github.com/godaddy/cobhan-python/
